README.rst
setup.cfg
setup.py
neuralpy/__init__.py
neuralpy/activations.py
neuralpy/colors.py
neuralpy/costs.py
neuralpy/data.py
neuralpy/neural2.py
neuralpy.egg-info/PKG-INFO
neuralpy.egg-info/SOURCES.txt
neuralpy.egg-info/dependency_links.txt
neuralpy.egg-info/requires.txt
neuralpy.egg-info/top_level.txt
neuralpy/iterators/__init__.py
neuralpy/iterators/iterator.py
neuralpy/iterators/layer_iterator.py
neuralpy/layers/__init__.py
neuralpy/layers/input_.py
neuralpy/layers/layer.py
neuralpy/layers/mlp.py