Metadata-Version: 1.1
Name: neuralpy
Version: 1.3.0
Summary: neuralpy - The most intuitive Neural Network Model
Home-page: https://github.com/jon--lee/neuralpy
Author: Jonathan N. Lee
Author-email: jonathan_lee@berkeley.edu
License: MIT
Keywords: neuralpy neural networks
Platform: UNKNOWN
Classifier: Development Status :: 3 - Alpha
Classifier: Intended Audience :: Developers
Classifier: Intended Audience :: Science/Research
Classifier: Topic :: Software Development
Classifier: Topic :: Scientific/Engineering
Classifier: Topic :: Scientific/Engineering :: Artificial Intelligence
Classifier: Programming Language :: Python
Classifier: Programming Language :: Python :: 2.7
